ascii_frame/__init__.py
ascii_frame/__main__.py
ascii_frame/ascii_frame.py
ascii_frame/chain.py
ascii_frame/textobject.py
ascii_frame/tests/__init__.py
ascii_frame/tests/test_api.py
ascii_frame/tests/test_textobject.py
ascii_frame-0.0.1.data/scripts/ascii_frame
ascii_frame-0.0.1.dist-info/DESCRIPTION.rst
ascii_frame-0.0.1.dist-info/METADATA
ascii_frame-0.0.1.dist-info/RECORD
ascii_frame-0.0.1.dist-info/WHEEL
ascii_frame-0.0.1.dist-info/metadata.json
ascii_frame-0.0.1.dist-info/top_level.txt
